MANIFEST.in
README.md
README.txt
setup.py
django_static_sitemaps.egg-info/PKG-INFO
django_static_sitemaps.egg-info/SOURCES.txt
django_static_sitemaps.egg-info/dependency_links.txt
django_static_sitemaps.egg-info/requires.txt
django_static_sitemaps.egg-info/top_level.txt
static_sitemaps/__init__.py
static_sitemaps/conf.py
static_sitemaps/generator.py
static_sitemaps/tasks.py
static_sitemaps/urls.py
static_sitemaps/util.py
static_sitemaps/views.py
static_sitemaps/management/__init__.py
static_sitemaps/management/commands/__init__.py
static_sitemaps/management/commands/refresh_sitemap.py
static_sitemaps/templates/static_sitemaps/sitemap_index.xml